LiveREPL/LiveREPL.py
LiveREPL/__init__.py
LiveREPL-1.0.0.dist-info/METADATA
LiveREPL-1.0.0.dist-info/WHEEL
LiveREPL-1.0.0.dist-info/top_level.txt
LiveREPL-1.0.0.dist-info/RECORD
