Metadata-Version: 2.1
Name: LiveREPL
Version: 1.0.0
Summary: A Python REPL that can be used without stopping your program's execution. Brought to you by the fine folks at PySimpleGUI.org
Home-page: https://github.com/PySimpleGUI/LiveREPL
Author: PySimpleGUI
Author-email: mike@PySimpleGUI.org
License: UNKNOWN
Keywords: GUI UI PySimpleGUI tkinter
Platform: UNKNOWN
Classifier: Programming Language :: Python :: 3
Classifier: Programming Language :: Python :: 3.4
Classifier: Programming Language :: Python :: 3.5
Classifier: Programming Language :: Python :: 3.6
Classifier: Programming Language :: Python :: 3.7
Classifier: License :: OSI Approved :: GNU Lesser General Public License v3 or later (LGPLv3+)
Classifier: Topic :: Multimedia :: Graphics
Classifier: Operating System :: OS Independent
Requires-Dist: PySimpleGUI
